MANIFEST.in
README.md
requirements.txt
setup.py
EcoFin/__init__.py
EcoFin.egg-info/PKG-INFO
EcoFin.egg-info/SOURCES.txt
EcoFin.egg-info/dependency_links.txt
EcoFin.egg-info/requires.txt
EcoFin.egg-info/top_level.txt
EcoFin/assetAllocation/[!]blackLitterman.py
EcoFin/assetAllocation/__init__.py
EcoFin/assetAllocation/allocation.py
EcoFin/assetAllocation/markowitzModel.py
EcoFin/assetAllocation/performance.py
EcoFin/dataDownload/__init__.py
EcoFin/dataDownload/cache.py
EcoFin/dataDownload/core.py
EcoFin/dataDownload/functions.py
EcoFin/dataDownload/optionsManager.py
EcoFin/dataDownload/rates.py
EcoFin/dataDownload/shared.py
EcoFin/dataDownload/ticker.py
EcoFin/equity/__init__.py
EcoFin/equity/equity.py
EcoFin/forward/__init__.py
EcoFin/forward/forward.py
EcoFin/math/__init__.py
EcoFin/math/utils.py
EcoFin/math/stochasticProcess/__init__.py
EcoFin/math/stochasticProcess/itoProcess.py
EcoFin/math/stochasticProcess/process.py
EcoFin/options/__init__.py
EcoFin/options/binomialTree.py
EcoFin/options/blackScholesModel.py
EcoFin/options/chainWeights.py
EcoFin/options/deepOptionChain.py
EcoFin/options/deepOptionSurface.py
EcoFin/options/equityVIX.py
EcoFin/options/impliedVolatility.py
EcoFin/options/optionChain.py
EcoFin/options/optionChainSynopsis.py
EcoFin/options/optionSurface.py
EcoFin/options/utils.py
EcoFin/options/volatilitySmile.py
EcoFin/stat/[!]findTheoricalDistribution.py
EcoFin/stat/__init__.py
EcoFin/stat/empiricalDist.py
EcoFin/stat/equityVolatility.py
EcoFin/stat/interpolation.py
EcoFin/stat/montecarloDistribution.py
EcoFin/stat/utils.py
EcoFin/utils/__init__.py
EcoFin/utils/utils.py
Examples/!_optionPriceCurve.py
Examples/!_optionPriceSurface.py
Examples/VIX.py
Examples/__init__.py
Examples/americanOptionPricing.py
Examples/binomialTree.py
Examples/blackSholesPrice.py
Examples/deepOptionChain.py
Examples/exerciseProbability.py
Examples/historyVIX.py
Examples/impliedProbability.py
Examples/impliedVolatility.py
Examples/impliedVolatilityCurve.py
Examples/impliedVolatilitySpread.py
Examples/markowitzAllocation.py
Examples/maturityCheck.py
Examples/montecarloDistribution.py
Examples/montecarloSimulation.py
