Metadata-Version: 2.1
Name: EcoFin
Version: 1.2
Summary: EcoFin is a quantitative economic library
Home-page: https://github.com/LucaCamerani/EcoFin-Library
Author: Luca Camerani
Author-email: l.camerani@campus.unimib.it
License: BSD Open Source License
Platform: UNKNOWN
